log_control_ao/__init__.py
log_control_ao/version.py
log_control_ao/infrastructure/__init__.py
log_control_ao/infrastructure/ao.py
log_control_ao/infrastructure/do.py
log_control_ao-0.0.11.dist-info/LICENSE
log_control_ao-0.0.11.dist-info/METADATA
log_control_ao-0.0.11.dist-info/WHEEL
log_control_ao-0.0.11.dist-info/top_level.txt
log_control_ao-0.0.11.dist-info/RECORD
