Metadata-Version: 2.1
Name: log-control-ao
Version: 0.0.11
Summary: Exposed interface tool for accessing log controller api
Author: wangziling100
Author-email: wangziling100@163.com
Classifier: Programming Language :: Python :: 3
Classifier: License :: OSI Approved :: MIT License
License-File: LICENSE
